mcs_manager/__init__.py
mcs_manager/cli/__init__.py
mcs_manager/cli/wizard.py
mcs_manager/lib/__init__.py
mcs_manager/lib/client.py
mcs_manager/lib/config.py
mcs_manager/lib/enums.py
mcs_manager/lib/git.py
mcs_manager/lib/server.py
mcs_manager/main.py
mcs_manager-0.2.1.dist-info/LICENSE
mcs_manager-0.2.1.dist-info/METADATA
mcs_manager-0.2.1.dist-info/WHEEL
mcs_manager-0.2.1.dist-info/entry_points.txt
mcs_manager-0.2.1.dist-info/RECORD
